{
  "id": "r-202501310046-002",
  "reddit_id": "1ie1qvx",
  "source": "r",
  "timestamp": "2025-01-31T00:11:04",
  "tier": 1,
  "url": "https://reddit.com/r/coys/comments/1ie1qvx/fabrizio_romano_johan_lange_and_daniel_levy_are/",
  "title": "[Fabrizio Romano] \ud83d\udea8 Johan Lange and Daniel Levy are working on the Mathys Tel deal. The player has asked tonight for a few more hours to talk to his family and agent to decide whether he leaves on loan or permanently and to which club.",
  "content": "",
  "related_players": [],
  "related_clubs": [],
  "related_links": [],
  "sentiment": {
    "score": 0,
    "confidence": 0
  },
  "keywords": []
}